myfy/__init__.py
myfy/web/__init__.py
myfy/web/asgi.py
myfy/web/config.py
myfy/web/context.py
myfy/web/extensions.py
myfy/web/factory.py
myfy/web/handlers.py
myfy/web/module.py
myfy/web/routing.py
myfy/web/version.py
myfy_web-0.1.2.dist-info/METADATA
myfy_web-0.1.2.dist-info/WHEEL
myfy_web-0.1.2.dist-info/entry_points.txt
myfy_web-0.1.2.dist-info/RECORD
