Metadata-Version: 2.4
Name: myfy-web
Version: 0.1.2
Summary: Web/ASGI module for myfy framework
Requires-Python: >=3.12
Requires-Dist: myfy-core~=0.1.2
Requires-Dist: starlette>=0.40
